ZtjRedis.py
py_ztj_redis-1.0.0.dist-info/METADATA
py_ztj_redis-1.0.0.dist-info/WHEEL
py_ztj_redis-1.0.0.dist-info/top_level.txt
py_ztj_redis-1.0.0.dist-info/RECORD
