Metadata-Version: 2.1
Name: py-ztj-redis
Version: 1.0.0
Summary: python redis instance package
Home-page: https://github.com/ztj-package/py-redis
Author: ZhangTianJie
Author-email: ztj1993@gmail.com
License: MIT License
Keywords: redis
Platform: UNKNOWN
Requires-Dist: redis
